AUTHORS.rst
CHANGELOG.rst
LICENSE
MANIFEST.in
README.rst
setup.py
gallery/__init__.py
gallery/admin.py
gallery/admin_forms.py
gallery/admin_urls.py
gallery/admin_views.py
gallery/fields.py
gallery/generator.py
gallery/models.py
gallery/urls.py
gallery/widgets.py
gallery/fixtures/photosizes.json
gallery/locale/fr/LC_MESSAGES/django.mo
gallery/locale/fr/LC_MESSAGES/django.po
gallery/migrations/0001_initial.py
gallery/migrations/0002_auto__add_field_gallery_content.py
gallery/migrations/__init__.py
gallery/static/basic/gallery/css/gallery.css
gallery/static/basic/gallery/css/stub.txt
gallery/static/basic/gallery/js/gallery.js
gallery/static/smart/gallery/css/gallery.css
gallery/static/web/gallery/css/gallery.css
gallery/static/web/gallery/images/gallery-info.png
gallery/static/web/gallery/js/gallery.js
gallery/templates/admin/gallery/bulk_image_upload.html
gallery/templates/basic/gallery/inclusion_tags/gallery_detail.html
gallery/templates/basic/gallery/inclusion_tags/galleryimage_gallery_detail_collage.html
gallery/templates/basic/gallery/inclusion_tags/videoembed_detail.html
gallery/templates/basic/gallery/inclusion_tags/videoembed_gallery_detail_collage.html
gallery/templates/basic/gallery/inclusion_tags/videofile_gallery_detail_collage.html
gallery/templates/smart/gallery/inclusion_tags/gallery_detail.html
gallery/templates/smart/gallery/inclusion_tags/galleryimage_gallery_detail_collage.html
gallery/templates/smart/gallery/inclusion_tags/videoembed_gallery_detail_collage.html
gallery/templates/smart/gallery/inclusion_tags/videofile_gallery_detail_collage.html
gallery/templates/web/gallery/inclusion_tags/gallery_detail.html
gallery/templates/web/gallery/inclusion_tags/galleryimage_gallery_detail_collage.html
gallery/templates/web/gallery/inclusion_tags/videoembed_detail.html
gallery/templates/web/gallery/inclusion_tags/videoembed_gallery_detail_collage.html
gallery/templates/web/gallery/inclusion_tags/videofile_gallery_detail_collage.html
jmbo_gallery.egg-info/PKG-INFO
jmbo_gallery.egg-info/SOURCES.txt
jmbo_gallery.egg-info/dependency_links.txt
jmbo_gallery.egg-info/not-zip-safe
jmbo_gallery.egg-info/requires.txt
jmbo_gallery.egg-info/top_level.txt